[
  {
    "typ_oferty": "Bloki Światłowód",
    "opcje": [
      {
        "dlugosc_umowy": "24 miesiące",
        "opcje": [
          {
            "tytul": "200 Mb/s",
            "podtytul": "wysyłanie: 20 Mb/s",
            "cena": "50,00 zł",
            "wiecej_info": ["Aktywacja: 1 zł"]
          },
          {
            "tytul": "300 Mb/s",
            "podtytul": "wysyłanie: 30 Mb/s",
            "cena": "60,00 zł",
            "wiecej_info": ["Aktywacja: 1 zł"]
          },
          {
            "wyrozniony": true,
            "tytul": "500 Mb/s",
            "podtytul": "wysyłanie: 50 Mb/s",
            "cena": "70,00 zł",
            "wiecej_info": ["Aktywacja: 1 zł"]
          }
        ]
      },
      {
        "dlugosc_umowy": "12 miesięcy",
        "opcje": [
          {
            "tytul": "200 Mb/s",
            "podtytul": "wysyłanie: 20 Mb/s",
            "cena": "50,00 zł",
            "wiecej_info": ["Aktywacja: 99 zł"]
          },
          {
            "tytul": "300 Mb/s",
            "podtytul": "wysyłanie: 30 Mb/s",
            "cena": "60,00 zł",
            "wiecej_info": ["Aktywacja: 99 zł"]
          },
          {
            "wyrozniony": true,
            "tytul": "500 Mb/s",
            "podtytul": "wysyłanie: 50 Mb/s",
            "cena": "70,00 zł",
            "wiecej_info": ["Aktywacja: 99 zł"]
          }
        ]
      },
      {
        "dlugosc_umowy": "czas nieokreślony",
        "opcje": [
          {
            "tytul": "100 Mb/s",
            "podtytul": "wysyłanie: 10 Mb/s",
            "cena": "50,00 zł",
            "wiecej_info": ["Aktywacja: 99 zł"]
          }
        ]
      }
    ]
  },
  {
    "typ_oferty": "Domki Światłowód",
    "opcje": [
      {
        "dlugosc_umowy": "24 miesiące",
        "opcje": [
          {
            "tytul": "Standard",
            "podtytul": "odbieranie: 200 Mb/s\nwysyłanie: 20 Mb/s",
            "cena": "60,00 zł",
            "wiecej_info": ["Aktywacja: 1 zł"]
          },
          {
            "tytul": "Plus",
            "podtytul": "odbieranie: 300 Mb/s\nwysyłanie: 30 Mb/s",
            "cena": "70,00 zł",
            "wiecej_info": ["Aktywacja: 1 zł"]
          },
          {
            "wyrozniony": true,
            "tytul": "Super",
            "podtytul": "odbieranie: 800 Mb/s\nwysyłanie: 50 Mb/s",
            "cena": "100,00 zł",
            "wiecej_info": ["Aktywacja: 1 zł"]
          }
        ]
      }
    ]
  },
  {
    "typ_oferty": "NEXERA Światłowód",
    "opcje": [
      {
        "dlugosc_umowy": "24 miesiące",
        "opcje": [
          {
            "wyrozniony": true,
            "tytul": "Super",
            "podtytul": "odbieranie: 300 Mb/s\nwysyłanie: 30 Mb/s",
            "cena": "70,00 zł",
            "wiecej_info": ["Aktywacja: 1 zł"]
          }
        ]
      }
    ]
  }
]
